ampliseek/__init__.py
ampliseek/ampliseek.py
AmpliSeek-0.1.5.dist-info/LICENSE
AmpliSeek-0.1.5.dist-info/METADATA
AmpliSeek-0.1.5.dist-info/WHEEL
AmpliSeek-0.1.5.dist-info/entry_points.txt
AmpliSeek-0.1.5.dist-info/top_level.txt
AmpliSeek-0.1.5.dist-info/RECORD
