Metadata-Version: 2.1
Name: AmpliSeek
Version: 0.1.5
Summary: AmpliSeq amplicon mapper tool
Home-page: https://github.com/KaibondChau/ampliseek
Author: Kevin Chau
Author-email: kevin.chau@ndm.ox.ac.uk
License: LICENSE
Platform: UNKNOWN
Classifier: Intended Audience :: Science/Research
Classifier: License :: OSI Approved :: MIT License
Classifier: Natural Language :: English
Requires-Python: >=3.6
Requires-Dist: biopython
